rsuv3
