Metadata-Version: 1.0
Name: rsuv3
Version: 1.0.1
Summary: RSUV3 - Library for controlling RS-UV3 Radio Shield.
Home-page: https://github.com/ampledata/rsuv3
Author: Greg Albrecht
Author-email: gba@orionlabs.io
License: Copyright 2016 Orion Labs, Inc.
